README.md
setup.cfg
setup.py
bin/amend_spectroflat
bin/prepare
src/atlas_fit/__init__.py
src/atlas_fit/comperator.py
src/atlas_fit.egg-info/PKG-INFO
src/atlas_fit.egg-info/SOURCES.txt
src/atlas_fit.egg-info/dependency_links.txt
src/atlas_fit.egg-info/requires.txt
src/atlas_fit.egg-info/top_level.txt
src/atlas_fit/atlantes/__init__.py
src/atlas_fit/atlantes/atlas.py
src/atlas_fit/atlantes/hamburg.py
src/atlas_fit/atlantes/sss.py
src/atlas_fit/base/__init__.py
src/atlas_fit/base/config.py
src/atlas_fit/base/constants.py
src/atlas_fit/base/errors.py
src/atlas_fit/models/__init__.py
src/atlas_fit/models/differential_convolution.py
src/atlas_fit/models/model_convolution.py
src/atlas_fit/models/spectrum.py
src/atlas_fit/utils/__init__.py
src/atlas_fit/utils/corrections.py
src/atlas_fit/utils/fitting_functions.py
src/atlas_fit/utils/io.py
src/atlas_fit/utils/tailoring.py
src/atlas_fit/utils/utils.py