Metadata-Version: 2.1
Name: atlas-fit
Version: 1.0.0
Summary: Tool to perform comparison and calibration of flat fielded flat images against a solar atlas.
Home-page: https://gitlab.gwdg.de/hoelken/atlas-fit
Author: Johannes Hölken
Author-email: hoelken@mps.mpg.de
License: UNKNOWN
Project-URL: Bug Tracker, https://gitlab.gwdg.de/hoelken/atlas-fit/issues
Platform: UNKNOWN
Classifier: Programming Language :: Python :: 3
Classifier: License :: OSI Approved :: BSD License
Classifier: Operating System :: OS Independent
Requires-Python: >=3.8
